chaintools_bio/__init__.py
chaintools_bio/annotate.py
chaintools_bio/chain_filter.py
chaintools_bio/cli.py
chaintools_bio/invert.py
chaintools_bio/split.py
chaintools_bio/stats.py
chaintools_bio/test_utils.py
chaintools_bio/to_bed.py
chaintools_bio/to_paf.py
chaintools_bio/to_sam.py
chaintools_bio/to_vcf.py
chaintools_bio/utils.py
chaintools_bio-0.4.1.dist-info/METADATA
chaintools_bio-0.4.1.dist-info/WHEEL
chaintools_bio-0.4.1.dist-info/entry_points.txt
chaintools_bio-0.4.1.dist-info/licenses/LICENSE
chaintools_bio-0.4.1.dist-info/RECORD
