Metadata-Version: 2.4
Name: chaintools_bio
Version: 0.4.1
Summary: Utilities for the genomic chain format
Project-URL: Homepage, https://github.com/milkschen/chaintools_bio
Author: Nae-Chyun Chen (@milkschen), Nancy F. Hansen (@nhansen)
License-File: LICENSE
Classifier: License :: OSI Approved :: MIT License
Classifier: Operating System :: POSIX :: Linux
Classifier: Programming Language :: Python :: 3
Requires-Python: >=3.7
Requires-Dist: intervaltree>=3.1.0
Requires-Dist: pandas
Requires-Dist: pysam>=0.15.3
Requires-Dist: typer>=0.9.0
